{
  "作者": "菜妮丝https://cainisi.cf",
  "站名": "360影视",
  "主页url": "http://我不是.肥猫.love:63/cainisi//",
  "请求头": "cainisi",
  "强制解析": "1",
  
  "分类": "电影$1#电视剧$2#综艺$3#动漫$4",
  
  "分类url": "http://我不是.肥猫.love:63/cainisi/fl.php?id={cateId}&pg={catePg}&cat={class}&year={year}&area={area}&rank={by}&act={act}",
  
  "数组": "数组=&&=数组",
  "图片": "图片=\"&&\"",
  "标题": "标题=\"&&\"",
  "链接": "链接=\"&&\"",
  "副标题": "副标题=\"&&\"",
  
  "搜索模式": "1",
  "搜索url": "ss.php?wd={wd}",
  "搜索数组": "数组=&&=数组",
  "搜索图片": "图片=\"&&\"",
  "搜索标题": "标题=\"&&\"",
  "搜索链接": "链接=\"&&\"",
  "搜索副标题": "副标题=\"&&\"",
  
  "影片年代": "年份=\"&&\"",
  "影片地区": "地区=\"&&\"",
  "影片类型": "类型=\"&&\"",
  "导演": "导演=\"&&\"",
  "主演": "主演=\"&&\"",
  "简介": "简介=\"&&\"",
  
  "线路数组": "线路数组=&&=线路数组",
  "线路标题": "线路标题=\"&&\"",
  
  "播放数组": "播放数组=&&=播放数组",
  "播放列表": "播放列表=&&=播放列表",
  "播放标题": "播放标题=\"&&\"",
  "播放链接": "播放链接=\"&&\"",
  
  "筛选":{
"1":[
  {"key":"class","name":"剧情","value":[
  {"n":"全部","v":""},
  {"n":"喜剧","v":"喜剧"},
  {"n":"爱情","v":"爱情"},
  {"n":"动作","v":"动作"},
  {"n":"恐怖","v":"恐怖"},
  {"n":"科幻","v":"科幻"},
  {"n":"剧情","v":"剧情"},
  {"n":"犯罪","v":"犯罪"},
  {"n":"奇幻","v":"奇幻"},
  {"n":"战争","v":"战争"},
  {"n":"悬疑","v":"悬疑"},
  {"n":"动画","v":"动画"},
  {"n":"文艺","v":"文艺"},
  {"n":"纪录","v":"纪录"},
  {"n":"传记","v":"传记"},
  {"n":"歌舞","v":"歌舞"},
  {"n":"古装","v":"古装"},
  {"n":"历史","v":"历史"},
  {"n":"惊悚","v":"惊悚"},
  {"n":"伦理","v":"伦理"},
  {"n":"其他","v":"其他"}]},
  
  {"key":"area","name":"地区","value":[
  {"n":"全部","v":""},
  {"n":"内地","v":"大陆"},
  {"n":"中国香港","v":"香港"},
  {"n":"中国台湾","v":"台湾"},
  {"n":"泰国","v":"泰国"},
  {"n":"美国","v":"美国"},
  {"n":"韩国","v":"韩国"},
  {"n":"日本","v":"日本"},
  {"n":"法国","v":"法国"},
  {"n":"英国","v":"英国"},
  {"n":"德国","v":"德国"},
  {"n":"印度","v":"印度"},
  {"n":"其他","v":"其他"}]},
  
  {"key":"act","name":"明星","value":[
  {"n":"全部","v":""},
  {"n":"成龙","v":"成龙"},
  {"n":"周星驰","v":"周星驰"},
  {"n":"李连杰","v":"李连杰"},
  {"n":"林正英","v":"林正英"},
  {"n":"吴京","v":"吴京"},
  {"n":"徐峥","v":"徐峥"},
  {"n":"黄渤","v":"黄渤"},
  {"n":"王宝强","v":"王宝强"},
  {"n":"李小龙","v":"李小龙"},
  {"n":"张国荣","v":"张国荣"},
  {"n":"洪金宝","v":"洪金宝"},
  {"n":"姜文","v":"姜文"},
  {"n":"沈腾","v":"沈腾"},
  {"n":"邓超","v":"邓超"},
  {"n":"巩俐","v":"巩俐"},
  {"n":"马丽","v":"马丽"},
  {"n":"闫妮","v":"闫妮"},
  {"n":"周冬雨","v":"周冬雨"},
  {"n":"刘昊然","v":"刘昊然"},
  {"n":"汤唯","v":"汤唯"},
  {"n":"舒淇","v":"舒淇"},
  {"n":"白百何","v":"白百何"}]},
  
  {"key":"year","name":"年份","value":[
  {"n":"全部","v":""},
  {"n":"2023","v":"2023"},
  {"n":"2022","v":"2022"},
  {"n":"2021","v":"2021"},
  {"n":"2020","v":"2020"},
  {"n":"2019","v":"2019"},
  {"n":"2018","v":"2018"},
  {"n":"2017","v":"2017"},
  {"n":"2016","v":"2016"},
  {"n":"2015","v":"2015"},
  {"n":"2014","v":"2014"},
  {"n":"2013","v":"2013"},
  {"n":"2012","v":"2012"},
  {"n":"2010","v":"2010"},
  {"n":"2009","v":"2009"},
  {"n":"2008","v":"2008"},
  {"n":"2007","v":"2007"},
  {"n":"更早","v":"lt_year"}]},
  
  {"key":"by","name":"排序","value":[
  {"n":"最近热映","v":"rankhot"},
  {"n":"最近上映","v":"ranklatest"},
  {"n":"最受好评","v":"rankpoint"}]}],
  
"2":[
  {"